pysnakegym/game/__init__.py
pysnakegym/game/colour.py
pysnakegym/game/snake.py
pysnakegym/game/core/__init__.py
pysnakegym/game/core/direction.py
pysnakegym/game/core/grid.py
pysnakegym/game/core/point.py
pysnakegym/mdp/__init__.py
pysnakegym/mdp/mdp.py
pysnakegym/mdp/snake.py
pysnakegym/mdp/state.py
pysnakegym/model/__init__.py
pysnakegym/model/deep_q_network.py
pysnakegym/model/ffnn.py
pysnakegym/model/replay_memory.py
pysnakegym/model/simple_deep_q_network.py
pysnakegym-0.0.19.dist-info/METADATA
pysnakegym-0.0.19.dist-info/WHEEL
pysnakegym-0.0.19.dist-info/top_level.txt
pysnakegym-0.0.19.dist-info/RECORD
