Metadata-Version: 2.1
Name: pysnakegym
Version: 0.0.19
Summary: Gym for the Snake Game
Home-page: UNKNOWN
Author: Jonas Barth
Author-email: jonas.barth.95@gmail.com
License: UNKNOWN
Keywords: python,snake,game,video game
Platform: UNKNOWN
Classifier: Development Status :: 2 - Pre-Alpha
Classifier: Intended Audience :: Developers
Classifier: Programming Language :: Python :: 3.6
Classifier: Operating System :: Unix
Classifier: Operating System :: MacOS :: MacOS X
Classifier: Operating System :: Microsoft :: Windows
Requires-Dist: torch (==1.7.1)
Requires-Dist: numpy
Requires-Dist: scipy
Requires-Dist: pygame (==1.9.4)
Requires-Dist: pytest
